bof/__init__.py
bof/common.py
bof/feature_extraction.py
bof/fuzz.py
bof/numba.py
bof-0.4.2.dist-info/METADATA
bof-0.4.2.dist-info/WHEEL
bof-0.4.2.dist-info/licenses/AUTHORS.rst
bof-0.4.2.dist-info/RECORD
