Metadata-Version: 2.4
Name: bof
Version: 0.4.2
Summary: Bag of Factors allows you to analyze a corpus from its factors.
Project-URL: Repository, https://github.com/balouf/bof
Project-URL: Documentation, https://balouf.github.io/bof
Author-email: Fabien Mathieu <fabien.mathieu@normalesup.org>
Maintainer-email: Fabien Mathieu <fabien.mathieu@normalesup.org>
License-Expression: MIT
License-File: AUTHORS.rst
Requires-Python: >=3.11
Requires-Dist: dill>=0.3.8
Requires-Dist: numba>=0.63.0
Requires-Dist: scipy>=1.16.1
